{
  "id": "de-anima-aristotle",
  "title": {
    "fr": "De l'âme",
    "en": "On the Soul"
  },
  "originalTitle": "De Anima",
  "author": {
    "slug": "aristotle",
    "name": {
      "fr": "Aristote",
      "en": "Aristotle"
    }
  },
  "year": -350,
  "presentation": {
    "fr": "Traité, connu sous son titre latin De Anima, qui étudie l'âme comme principe de vie et forme du corps vivant, et analyse la perception et la pensée.",
    "en": "A treatise, known by its Latin title De Anima, that studies the soul as the principle of life and the form of the living body, and analyzes perception and thought."
  },
  "updatedAt": "2026-06-17T00:00:00.000Z"
}
