{
  "id": "des-hommes-que-nous-rencontrons-neuf-locke",
  "text": { "fr": "Des hommes que nous rencontrons, neuf sur dix sont ce qu'ils sont, bons ou mauvais, utiles ou non, par leur éducation.", "en": "Of all the men we meet with, nine parts of ten are what they are, good or evil, useful or not, by their education." },
  "author": { "name": { "fr": "Locke", "en": "Locke" }, "kind": "PHILOSOPHER", "slug": "locke" },
  "work": "some-thoughts-concerning-education-locke",
  "source": { "fr": "Quelques pensées sur l'éducation, §1", "en": "Some Thoughts Concerning Education, §1" },
  "anchors": [{ "axisId": "HUMAN_NATURE" }],
  "updatedAt": "2026-07-18T00:00:00.000Z"
}
