{
  "id": "je-ne-regarde-plus-avec-les-zhuangzi",
  "text": { "fr": "Je ne regarde plus avec les yeux mais avec l'esprit, et la lame suit d'elle-même les interstices naturels.", "en": "I no longer look with my eyes but with my spirit, and the blade follows of itself the natural openings." },
  "author": { "name": { "fr": "Zhuangzi", "en": "Zhuangzi" }, "kind": "PHILOSOPHER", "slug": "zhuangzi" },
  "source": { "fr": "ch. 3 (Principe vital)", "en": "ch. 3 (The Secret of Caring for Life)" },
  "anchors": [{ "axisId": "CONTROL_SCOPE", "poleId": "DICHOTOMY_OF_CONTROL" }],
  "updatedAt": "2026-07-18T00:00:00.000Z"
}
