{
  "id": "l-optimisme-quand-il-n-est-schopenhauer",
  "text": { "fr": "L'optimisme, quand il n'est pas le bavardage inconsidéré de ceux qui n'abritent que des mots sous leurs fronts plats, m'apparaît comme une manière de penser non seulement absurde, mais vraiment infâme : une amère dérision des souffrances innommables de l'humanité.", "en": "Optimism, when it is not merely the thoughtless talk of those who harbour nothing but words beneath their flat foreheads, seems to me not only an absurd but a truly wicked way of thinking: a bitter mockery of the unspeakable sufferings of humanity." },
  "author": { "name": { "fr": "Schopenhauer", "en": "Schopenhauer" }, "kind": "PHILOSOPHER", "slug": "schopenhauer" },
  "work": "the-world-as-will-and-representation-schopenhauer",
  "source": { "fr": "Le Monde comme volonté et comme représentation, §59", "en": "The World as Will and Representation, §59" },
  "anchors": [{ "axisId": "COSMIC_OUTLOOK" }],
  "updatedAt": "2026-07-18T00:00:00.000Z"
}
