{
  "id": "realism-universals-grounds-essentialism",
  "ground": { "axisId": "UNIVERSALS", "poleId": "REALISM" },
  "grounded": { "axisId": "ESSENCE", "poleId": "ESSENTIALISM" },
  "kind": "T_T",
  "strength": "STRONG",
  "explanation": {
    "fr": "Si les propriétés générales existent réellement et ne sont pas de simples noms, alors les choses ont une nature, une forme qui les définit en propre. Le réalisme des universaux fonde l'essentialisme : que les Idées subsistent à part (<ph id='plato'>Platon</ph>) ou dans les choses mêmes (<ph id='aristotle'>Aristote</ph>), l'essence d'un être est une réalité que la connaissance découvre.",
    "en": "If general properties really exist and are not mere names, then things have a nature, a form that defines them in their own right. Realism about universals grounds essentialism: whether the Forms subsist apart (<ph id='plato'>Plato</ph>) or within things themselves (<ph id='aristotle'>Aristotle</ph>), the essence of a being is a reality that knowledge discovers."
  },
  "updatedAt": "2026-06-22T00:00:00.000Z"
}
